py_rcon_shell/__init__.py
py_rcon_shell/constants.py
py_rcon_shell/rcon_client.py
py_rcon_shell/rcon_shell.py
py_rcon_shell/tests/__init__.py
py_rcon_shell/tests/test_rcon_shell.py
rcon_shell-0.0.1.dist-info/entry_points.txt
rcon_shell-0.0.1.dist-info/LICENSE
rcon_shell-0.0.1.dist-info/WHEEL
rcon_shell-0.0.1.dist-info/METADATA
rcon_shell-0.0.1.dist-info/RECORD
