Metadata-Version: 2.1
Name: rcon-shell
Version: 0.0.1
Summary: Minecraft rcon shell in Python
Home-page: https://github.com/jedie/PyRconShell
License: GNU General Public License v3.0
Author: Jens Diemer
Author-email: python@jensdiemer.de
Requires-Python: >=3.8,<4.0.0
Classifier: License :: Other/Proprietary License
Classifier: Programming Language :: Python :: 3
Classifier: Programming Language :: Python :: 3.8
Classifier: Programming Language :: Python :: 3.9
Requires-Dist: dev-shell
Requires-Dist: rcon
